src2prod/LICENSE.txt
src2prod/README.md
src2prod/__init__.py
src2prod/__main__.py
src2prod/baseproj.py
src2prod/project.py
src2prod-0.1.1b0.dist-info/WHEEL
src2prod-0.1.1b0.dist-info/entry_points.txt
src2prod-0.1.1b0.dist-info/METADATA
src2prod-0.1.1b0.dist-info/RECORD
