Metadata-Version: 2.1
Name: src2prod
Version: 0.1.1b0
Summary: This module allows to develop a project within a source folder and to publish the final product in another folder, this last directory being a "thin" version of the source one.
Home-page: https://github.com/bc-tools/for-dev/tree/main/src2prod
License: GNU License Version 3
Author: Christophe BAL
Maintainer: Christophe BAL
Requires-Python: >=3.8,<4.0
Classifier: License :: Other/Proprietary License
Classifier: Programming Language :: Python :: 3
Classifier: Programming Language :: Python :: 3.8
Classifier: Programming Language :: Python :: 3.9
Classifier: Programming Language :: Python :: 3.10
Classifier: Programming Language :: Python :: 3.11
Requires-Dist: click (>=7.1.2,<8.0.0)
Requires-Dist: multimd (>=0.1.0-beta.0,<0.2.0)
Requires-Dist: spkpb (>=0.0.10-beta.0,<0.0.11)
Project-URL: Repository, https://github.com/bc-tools/for-dev/tree/main/src2prod
